radiale/__init__.py
radiale/chromecast.py
radiale/deconz.py
radiale/esphome.py
radiale/mdns.py
radiale/mqtt.py
radiale/pod.py
radiale/schedule.py
radiale-0.5.2.dist-info/LICENSE
radiale-0.5.2.dist-info/METADATA
radiale-0.5.2.dist-info/WHEEL
radiale-0.5.2.dist-info/top_level.txt
radiale-0.5.2.dist-info/RECORD
