Metadata-Version: 2.1
Name: radiale
Version: 0.5.2
Summary: radiale
Home-page: https://github.com/xlfe/radiale
License: EPL
Keywords: home-automation
Platform: UNKNOWN
Classifier: Development Status :: 3 - Alpha
Classifier: Intended Audience :: Developers
Classifier: Topic :: Home Automation
Classifier: License :: OSI Approved :: Eclipse Public License 2.0 (EPL-2.0)
Classifier: Programming Language :: Python :: 3.9
License-File: LICENSE
Requires-Dist: websockets
Requires-Dist: aiohttp
Requires-Dist: pychromecast
Requires-Dist: aioesphomeapi
Requires-Dist: zeroconf
Requires-Dist: bcoding
Requires-Dist: asyncio-mqtt
Requires-Dist: boltons
Requires-Dist: celery
Requires-Dist: astral
Requires-Dist: pytz
